pretty_pie_log/__init__.py
pretty_pie_log/pie_log_level.py
pretty_pie_log/pie_logger.py
pretty_pie_log-0.3.14.dist-info/licenses/LICENSE
pretty_pie_log-0.3.14.dist-info/METADATA
pretty_pie_log-0.3.14.dist-info/WHEEL
pretty_pie_log-0.3.14.dist-info/top_level.txt
pretty_pie_log-0.3.14.dist-info/RECORD
