Metadata-Version: 2.4
Name: pretty_pie_log
Version: 0.3.14
Summary: A feature-rich logging utility that provides colorized console output with customizable formatting
Author: chanpreet3000
License: MIT
Project-URL: Homepage, https://github.com/chanpreet3000/pretty-pie-log
Project-URL: Bug Tracker, https://github.com/chanpreet3000/pretty-pie-log/issues
Project-URL: Source Code, https://github.com/chanpreet3000/pretty-pie-log
Keywords: logging,colorized,console,debug,formatting,pretty-print,thread-safe,timezone,structured-logging
Classifier: Development Status :: 3 - Alpha
Classifier: Intended Audience :: Developers
Classifier: Topic :: Software Development :: Libraries :: Python Modules
Classifier: Topic :: System :: Logging
Classifier: Programming Language :: Python :: 3
Classifier: Programming Language :: Python :: 3.7
Classifier: Programming Language :: Python :: 3.8
Classifier: Programming Language :: Python :: 3.9
Classifier: Programming Language :: Python :: 3.10
Classifier: Programming Language :: Python :: 3.11
Classifier: License :: OSI Approved :: MIT License
Classifier: Operating System :: OS Independent
Requires-Python: >=3.7
License-File: LICENSE
Requires-Dist: colorama>=0.4.6
Requires-Dist: pytz>=2024.2
Dynamic: license-file
